jupyter_web_report/__init__.py
jupyter_web_report/jupyter_web_report.py
jupyter_web_report-0.2.2.data/data/example/data_mutation.txt
jupyter_web_report-0.2.2.data/data/example/model.ipynb
jupyter_web_report-0.2.2.data/data/imgs/jupyter_lab.jpg
jupyter_web_report-0.2.2.data/data/imgs/template_notebook_configuration.gif
jupyter_web_report-0.2.2.data/data/imgs/template_notebook_configuration2.gif
jupyter_web_report-0.2.2.data/data/imgs/template_notebook_configuration3.gif
jupyter_web_report-0.2.2.dist-info/LICENSE
jupyter_web_report-0.2.2.dist-info/METADATA
jupyter_web_report-0.2.2.dist-info/WHEEL
jupyter_web_report-0.2.2.dist-info/entry_points.txt
jupyter_web_report-0.2.2.dist-info/top_level.txt
jupyter_web_report-0.2.2.dist-info/RECORD
