Metadata-Version: 2.1
Name: jupyter-web-report
Version: 0.2.2
Summary: jupyter web report
Home-page: https://github.com/JaylanLiu/jupyter-web-report
Author: JaylanLiu
Author-email: liujilong@outlook.com
License: UNKNOWN
Platform: UNKNOWN
Classifier: Development Status :: 3 - Alpha
Classifier: Intended Audience :: Developers
Classifier: Topic :: Scientific/Engineering :: Bio-Informatics
Classifier: License :: OSI Approved :: MIT License
Classifier: Programming Language :: Python :: 3.5
Classifier: Programming Language :: Python :: 3.6
Classifier: Programming Language :: Python :: 3.7
Requires-Python: >=3.6
License-File: LICENSE
Requires-Dist: nbconvert
Requires-Dist: mistune
Requires-Dist: ipython-genutils
Requires-Dist: argparse
